probables/__init__.py
probables/constants.py
probables/exceptions.py
probables/hashes.py
probables/py.typed
probables/utilities.py
probables/blooms/__init__.py
probables/blooms/bloom.py
probables/blooms/countingbloom.py
probables/blooms/expandingbloom.py
probables/blooms/py.typed
probables/countminsketch/__init__.py
probables/countminsketch/countminsketch.py
probables/countminsketch/py.typed
probables/cuckoo/__init__.py
probables/cuckoo/countingcuckoo.py
probables/cuckoo/cuckoo.py
probables/cuckoo/py.typed
probables/quotientfilter/__init__.py
probables/quotientfilter/py.typed
probables/quotientfilter/quotientfilter.py
pyprobables-0.6.1.dist-info/LICENSE
pyprobables-0.6.1.dist-info/METADATA
pyprobables-0.6.1.dist-info/WHEEL
pyprobables-0.6.1.dist-info/top_level.txt
pyprobables-0.6.1.dist-info/RECORD
