Metadata-Version: 2.1
Name: pyprobables
Version: 0.6.1
Summary: Probabilistic data structures in python
Author-email: Tyler Barrus <barrust@gmail.com>
License: MIT
Project-URL: Homepage, https://github.com/barrust/pyprobables
Project-URL: Bug-tracker, https://github.com/barrust/pyprobables/issues
Project-URL: Documentation, https://pyprobables.readthedocs.io/
Keywords: python,probabilistic,data-structure,bloom,filter,count-min,sketch,bloom-filter,count-min-sketch,cuckoo-filter,quotient-filter
Classifier: Development Status :: 5 - Production/Stable
Classifier: Intended Audience :: Developers
Classifier: Intended Audience :: Information Technology
Classifier: Intended Audience :: Science/Research
Classifier: Topic :: Software Development :: Libraries
Classifier: Topic :: Utilities
Classifier: License :: OSI Approved
Classifier: License :: OSI Approved :: MIT License
Classifier: Programming Language :: Python
Classifier: Programming Language :: Python :: 3
Classifier: Programming Language :: Python :: 3.8
Classifier: Programming Language :: Python :: 3.9
Classifier: Programming Language :: Python :: 3.10
Classifier: Programming Language :: Python :: 3.11
Classifier: Programming Language :: Python :: 3.12
Requires-Python: >=3.8
License-File: LICENSE
